at_scat.cpython-37m-darwin.so
ftran.cpython-37m-darwin.so
gbm_drm_gen/__init__.py
gbm_drm_gen/__version__.py
gbm_drm_gen/basersp.py
gbm_drm_gen/detdatabase.py
gbm_drm_gen/drmgen.py
gbm_drm_gen/drmgen_trig.py
gbm_drm_gen/drmgen_tte.py
gbm_drm_gen/io/__init__.py
gbm_drm_gen/io/balrog_drm.py
gbm_drm_gen/io/balrog_healpix_map.py
gbm_drm_gen/io/balrog_like.py
gbm_drm_gen/io/palantir.py
gbm_drm_gen/io/response_generator.py
gbm_drm_gen/utils/__init__.py
gbm_drm_gen/utils/_create_database.py
gbm_drm_gen/utils/contour_finder.py
gbm_drm_gen/utils/file_utils.py
gbm_drm_gen/utils/general_utils.py
gbm_drm_gen/utils/geometry.py
gbm_drm_gen/utils/package_data.py
gbm_drm_gen/utils/response.py
gbm_drm_gen-0.2.0.dist-info/LICENSE
gbm_drm_gen-0.2.0.dist-info/METADATA
gbm_drm_gen-0.2.0.dist-info/WHEEL
gbm_drm_gen-0.2.0.dist-info/top_level.txt
gbm_drm_gen-0.2.0.dist-info/RECORD
