Metadata-Version: 2.1
Name: gbm-drm-gen
Version: 0.2.0
Summary: A DRM generator for the Fermi GBM detectors
Home-page: https://github.com/mpe-grb/gbm_drm_gen
Author: J. Michael Burgess
Author-email: jmichaelburgess@gmail.com
License: BSD
Platform: UNKNOWN
Requires-Python: >=2.7.0
Requires-Dist: numpy
Requires-Dist: astropy
Requires-Dist: scipy
Requires-Dist: h5py
Requires-Dist: responsum
Requires-Dist: gbmgeometry
